gears/__init__.py
gears/data_utils.py
gears/gears.py
gears/inference.py
gears/model.py
gears/pertdata.py
gears/utils.py
gears/version.py
cell_gears-0.1.2.dist-info/LICENSE
cell_gears-0.1.2.dist-info/METADATA
cell_gears-0.1.2.dist-info/WHEEL
cell_gears-0.1.2.dist-info/top_level.txt
cell_gears-0.1.2.dist-info/RECORD
