Metadata-Version: 2.1
Name: cell-gears
Version: 0.1.2
Summary: GEARS
Home-page: https://github.com/snap-stanford/GEARS
Author: Yusuf Roohani, Kexin Huang, Jure Leskovec
License: MIT
License-File: LICENSE
Requires-Dist: numpy
Requires-Dist: pandas
Requires-Dist: tqdm
Requires-Dist: scikit-learn
Requires-Dist: torch
Requires-Dist: scanpy
Requires-Dist: networkx
Requires-Dist: dcor
